neuronvisio/__init__.py
neuronvisio/colorbutton.py
neuronvisio/command_line.py
neuronvisio/controls.py
neuronvisio/manager.py
neuronvisio/res.py
neuronvisio/visio.py
neuronvisio/modeldb/BeautifulSoup.py
neuronvisio/modeldb/ModelDB.py
neuronvisio/modeldb/ModelDB.xml
neuronvisio/modeldb/ModelsTree.py
neuronvisio/modeldb/Updater.py
neuronvisio/modeldb/__init__.py
neuronvisio/ui/neuronvisio.ui
neuronvisio/ui/qtAbout.ui
neuronvisio-0.9.1.dist-info/DESCRIPTION.rst
neuronvisio-0.9.1.dist-info/METADATA
neuronvisio-0.9.1.dist-info/RECORD
neuronvisio-0.9.1.dist-info/WHEEL
neuronvisio-0.9.1.dist-info/entry_points.txt
neuronvisio-0.9.1.dist-info/metadata.json
neuronvisio-0.9.1.dist-info/top_level.txt
