Metadata-Version: 2.0
Name: neuronvisio
Version: 0.9.1
Summary: Neuronvisio is a Graphical User Interface for NEURON simulator environment
Home-page: http://neuronvisio.org
Author: ['Michele Mattioni', 'Uri Cohen']
Author-email: ['<mattioni@ebi.ac.uk>', '<uri.cohen@alice.nc.huji.ac.il>']
License: GPLv3
Keywords: neuron,gui,pylab,3D,visualization
Platform: UNKNOWN
Classifier: Development Status :: 4 - Beta
Classifier: Programming Language :: Python
Classifier: Topic :: Scientific/Engineering :: Visualization
Requires-Dist: pip
Requires-Dist: setuptools
